azure/mgmt/chaos/__init__.py
azure/mgmt/chaos/_chaos_management_client.py
azure/mgmt/chaos/_configuration.py
azure/mgmt/chaos/_patch.py
azure/mgmt/chaos/_version.py
azure/mgmt/chaos/py.typed
azure/mgmt/chaos/_utils/__init__.py
azure/mgmt/chaos/_utils/serialization.py
azure/mgmt/chaos/aio/__init__.py
azure/mgmt/chaos/aio/_chaos_management_client.py
azure/mgmt/chaos/aio/_configuration.py
azure/mgmt/chaos/aio/_patch.py
azure/mgmt/chaos/aio/operations/__init__.py
azure/mgmt/chaos/aio/operations/_capabilities_operations.py
azure/mgmt/chaos/aio/operations/_capability_types_operations.py
azure/mgmt/chaos/aio/operations/_experiments_operations.py
azure/mgmt/chaos/aio/operations/_operation_statuses_operations.py
azure/mgmt/chaos/aio/operations/_operations.py
azure/mgmt/chaos/aio/operations/_patch.py
azure/mgmt/chaos/aio/operations/_target_types_operations.py
azure/mgmt/chaos/aio/operations/_targets_operations.py
azure/mgmt/chaos/models/__init__.py
azure/mgmt/chaos/models/_chaos_management_client_enums.py
azure/mgmt/chaos/models/_models_py3.py
azure/mgmt/chaos/models/_patch.py
azure/mgmt/chaos/operations/__init__.py
azure/mgmt/chaos/operations/_capabilities_operations.py
azure/mgmt/chaos/operations/_capability_types_operations.py
azure/mgmt/chaos/operations/_experiments_operations.py
azure/mgmt/chaos/operations/_operation_statuses_operations.py
azure/mgmt/chaos/operations/_operations.py
azure/mgmt/chaos/operations/_patch.py
azure/mgmt/chaos/operations/_target_types_operations.py
azure/mgmt/chaos/operations/_targets_operations.py
azure_mgmt_chaos-2.0.0.dist-info/LICENSE
azure_mgmt_chaos-2.0.0.dist-info/LICENSE.txt
azure_mgmt_chaos-2.0.0.dist-info/METADATA
azure_mgmt_chaos-2.0.0.dist-info/WHEEL
azure_mgmt_chaos-2.0.0.dist-info/top_level.txt
azure_mgmt_chaos-2.0.0.dist-info/RECORD
